tensorview/__init__.py
tensorview/model/__init__.py
tensorview/model/_statistics.py
tensorview/model/_visualize.py
tensorview/train/_PlotMetrics.py
tensorview/train/__init__.py
tensorview/train/_keras_callbacks_PlotMetricsOnBatch.py
tensorview/train/_keras_callbacks_PlotMetricsOnEpoch.py
tensorview/watch/__init__.py
tensorview/watch/_watch_image.py
tensorview-0.4.1.dist-info/LICENSE.txt
tensorview-0.4.1.dist-info/METADATA
tensorview-0.4.1.dist-info/WHEEL
tensorview-0.4.1.dist-info/top_level.txt
tensorview-0.4.1.dist-info/RECORD
