Metadata-Version: 2.1
Name: tensorview
Version: 0.4.1
Summary: Dynamic visualization training service in Jupyter Notebook for Keras tf.keras and others.
Home-page: https://github.com/Hourout/tensorview
Author: JinQing Lee
Author-email: hourout@163.com
License: Apache License Version 2.0
Keywords: keras-visualization,tensorflow-visualization,keras,tensorflow,tf.keras,plot,chart
Platform: UNKNOWN
Classifier: Framework :: Jupyter
Classifier: Intended Audience :: Developers
Classifier: Intended Audience :: Education
Classifier: Intended Audience :: Science/Research
Classifier: License :: OSI Approved :: Apache Software License
Classifier: Topic :: Scientific/Engineering
Classifier: Topic :: Scientific/Engineering :: Artificial Intelligence
Classifier: Topic :: Scientific/Engineering :: Visualization
Classifier: Programming Language :: Python :: 3.6
Classifier: Programming Language :: Python :: 3.7
Requires-Dist: matplotlib
Requires-Dist: pandas (>=0.24.1)
Requires-Dist: pyecharts (>=1.2.0)
Requires-Dist: pyecharts-snapshot (>=0.1.10tensorflow>=2.0.0)
Requires-Dist: linora (>=0.9.3)
